CHANGES.txt
COPYRIGHT.txt
LICENSE.txt
README.txt
base.cfg
setup.py
src/gocept/__init__.py
src/gocept.download.egg-info/PKG-INFO
src/gocept.download.egg-info/SOURCES.txt
src/gocept.download.egg-info/dependency_links.txt
src/gocept.download.egg-info/entry_points.txt
src/gocept.download.egg-info/namespace_packages.txt
src/gocept.download.egg-info/requires.txt
src/gocept.download.egg-info/top_level.txt
src/gocept/download/README.txt
src/gocept/download/__init__.py
src/gocept/download/sample.tar.gz
src/gocept/download/tests.py