Metadata-Version: 1.0
Name: gocept.download
Version: 0.9.5
Summary: zc.buildout recipe for downloading and extracting an archive.
Home-page: http://svn.gocept.com/repos/gocept/gocept.download
Author: Christian Theune
Author-email: ct@gocept.com
License: ZPL 2.1
Keywords: buildout zc.buildout recipe download extract archive
Platform: UNKNOWN
Classifier: Environment :: Console
Classifier: Environment :: Plugins
Classifier: Framework :: Buildout
Classifier: Intended Audience :: Developers
Classifier: Intended Audience :: System Administrators
Classifier: License :: OSI Approved :: Zope Public License
Classifier: Operating System :: OS Independent
Classifier: Programming Language :: Python
Classifier: Topic :: Software Development :: Build Tools
Classifier: Topic :: System :: Software Distribution
